findkw/__init__.py
findkw/findkw.py
findkw/findkw2.py
findkw-0.3.3.dist-info/LICENSE
findkw-0.3.3.dist-info/METADATA
findkw-0.3.3.dist-info/WHEEL
findkw-0.3.3.dist-info/entry_points.txt
findkw-0.3.3.dist-info/top_level.txt
findkw-0.3.3.dist-info/RECORD
