Metadata-Version: 2.1
Name: findkw
Version: 0.3.3
Summary: find the files or words
Home-page: https://github.com/ga1008/finder
Author: Guardian
Author-email: zhling2012@live.com
Maintainer: Guardian
Maintainer-email: zhling2012@live.com
License: UNKNOWN
Platform: UNKNOWN
Classifier: Programming Language :: Python :: 3
Classifier: License :: OSI Approved :: MIT License
Classifier: Operating System :: OS Independent
License-File: LICENSE
Requires-Dist: basecolors
Requires-Dist: colorama
Requires-Dist: chardet
